tmate/__init__.py
tmate/__main__.py
tmate/client.py
tmate/shell.py
tmate/utils.py
tmate-0.1.5.dist-info/METADATA
tmate-0.1.5.dist-info/WHEEL
tmate-0.1.5.dist-info/entry_points.txt
tmate-0.1.5.dist-info/top_level.txt
tmate-0.1.5.dist-info/RECORD
